<Properties StartupConfiguration="{5D5B2C02-32C2-F5A6-1044-74B4755F30D7}|">
  <MonoDevelop.Ide.Workbench ActiveDocument="Assets/SB/Scripts/Timer.cs">
    <Files>
      <File FileName="Assets/SB/Scripts/RecipeManager.cs" Line="29" Column="33" />
      <File FileName="Assets/SB/Scripts/ScoreManager.cs" />
      <File FileName="Assets/script/HamburgerManager.cs" />
      <File FileName="Assets/script/Reset.cs" />
      <File FileName="Assets/script/Restart.cs" />
      <File FileName="Assets/script/SpawnManager.cs" />
      <File FileName="Assets/SB/Scripts/GameManager.cs" />
      <File FileName="Assets/script/hamburgerMove.cs" />
      <File FileName="Assets/SB/Scripts/Timer.cs" Line="11" Column="35" />
      <File FileName="Assets/SB/Scripts/ExpSlider.cs" />
      <File FileName="Assets/SB/Scripts/TimerSlider.cs" />
      <File FileName="Assets/script/CustomerManager.cs" />
      <File FileName="Assets/script/Effect.cs" />
      <File FileName="Assets/SB/Scripts/recipeTimer.cs" />
    </Files>
    <Pads>
      <Pad Id="ProjectPad">
        <State name="__root__">
          <Node name="hamburger_prototype2-2" expanded="True">
            <Node name="Assets" expanded="True">
              <Node name="SB" expanded="True">
                <Node name="Scripts" expanded="True">
                  <Node name="Timer.cs" selected="True" />
                </Node>
              </Node>
              <Node name="script" expanded="True" />
            </Node>
          </Node>
        </State>
      </Pad>
    </Pads>
  </MonoDevelop.Ide.Workbench>
  <MonoDevelop.Ide.DebuggingService.PinnedWatches />
  <MonoDevelop.Ide.Workspace ActiveConfiguration="Debug" />
  <MonoDevelop.Ide.ItemProperties.Assembly-CSharp PreferredExecutionTarget="d7db0ded-e41b-4362-b42c-20e1020c28fa" />
  <MonoDevelop.Ide.DebuggingService.Breakpoints>
    <BreakpointStore />
  </MonoDevelop.Ide.DebuggingService.Breakpoints>
  <MultiItemStartupConfigurations />
</Properties>